cheesefactory
