Metadata-Version: 1.1
Name: cheesefactory
Version: 0.19
Summary: Wrappers for report-making with dataframes.
Home-page: https://bitbucket.org/thespectaculars/cheeseshop.git/wiki
Author: Todd Salazar
Author-email: unixsal@yahoo.com
License: UNKNOWN
Keywords: reports development
Platform: UNKNOWN
Classifier: Development Status :: 3 - Alpha
Classifier: Intended Audience :: Developers
Classifier: License :: OSI Approved :: BSD License
Classifier: Programming Language :: Python :: 3.6
